[
{
    "id": 1,
    "recv": [
        {
            "interface": "deposit",
            "result": "success"
        },
        {
            "interface": "query",
            "result": "",
            "balance": 410
        }
    ]
},
{
    "id": 2,
    "recv": [
        {
            "interface": "deposit",
            "result": "success"
        },
        {
            "interface": "query",
            "result": "",
            "balance": 420
        }
    ]
},
{
    "id": 3,
    "recv": [
        {
            "interface": "deposit",
            "result": "success"
        },
        {
            "interface": "query",
            "result": "",
            "balance": 430
        }
    ]
},
{
    "id": 4,
    "recv": [
        {
            "interface": "deposit",
            "result": "success"
        },
        {
            "interface": "query",
            "result": "",
            "balance": 440
        }
    ]
},
{
    "id": 5,
    "recv": [
        {
            "interface": "deposit",
            "result": "success"
        },
        {
            "interface": "query",
            "result": "",
            "balance": 450
        }
    ]
},
{
    "id": 6,
    "recv": [
        {
            "interface": "deposit",
            "result": "success"
        },
        {
            "interface": "query",
            "result": "",
            "balance": 460
        }
    ]
},
{
    "id": 7,
    "recv": [
        {
            "interface": "deposit",
            "result": "success"
        },
        {
            "interface": "query",
            "result": "",
            "balance": 470
        }
    ]
},
{
    "id": 8,
    "recv": [
        {
            "interface": "deposit",
            "result": "success"
        },
        {
            "interface": "query",
            "result": "",
            "balance": 480
        }
    ]
},
{
    "id": 9,
    "recv": [
        {
            "interface": "deposit",
            "result": "success"
        },
        {
            "interface": "query",
            "result": "",
            "balance": 490
        }
    ]
},
{
    "id": 10,
    "recv": [
        {
            "interface": "deposit",
            "result": "success"
        },
        {
            "interface": "query",
            "result": "",
            "balance": 500
        }
    ]
},
{
    "id": 11,
    "recv": [
        {
            "interface": "deposit",
            "result": "success"
        },
        {
            "interface": "query",
            "result": "",
            "balance": 510
        }
    ]
},
{
    "id": 12,
    "recv": [
        {
            "interface": "deposit",
            "result": "success"
        },
        {
            "interface": "query",
            "result": "",
            "balance": 520
        }
    ]
},
{
    "id": 13,
    "recv": [
        {
            "interface": "deposit",
            "result": "success"
        },
        {
            "interface": "query",
            "result": "",
            "balance": 530
        }
    ]
},
{
    "id": 14,
    "recv": [
        {
            "interface": "deposit",
            "result": "success"
        },
        {
            "interface": "query",
            "result": "",
            "balance": 540
        }
    ]
},
{
    "id": 15,
    "recv": [
        {
            "interface": "deposit",
            "result": "success"
        },
        {
            "interface": "query",
            "result": "",
            "balance": 550
        }
    ]
},
{
    "id": 16,
    "recv": [
        {
            "interface": "deposit",
            "result": "success"
        },
        {
            "interface": "query",
            "result": "",
            "balance": 560
        }
    ]
},
{
    "id": 17,
    "recv": [
        {
            "interface": "deposit",
            "result": "success"
        },
        {
            "interface": "query",
            "result": "",
            "balance": 570
        }
    ]
},
{
    "id": 18,
    "recv": [
        {
            "interface": "deposit",
            "result": "success"
        },
        {
            "interface": "query",
            "result": "",
            "balance": 580
        }
    ]
},
{
    "id": 19,
    "recv": [
        {
            "interface": "deposit",
            "result": "success"
        },
        {
            "interface": "query",
            "result": "",
            "balance": 590
        }
    ]
},
{
    "id": 20,
    "recv": [
        {
            "interface": "deposit",
            "result": "success"
        },
        {
            "interface": "query",
            "result": "",
            "balance": 600
        }
    ]
},
{
    "id": 21,
    "recv": [
        {
            "interface": "deposit",
            "result": "success"
        },
        {
            "interface": "query",
            "result": "",
            "balance": 610
        }
    ]
},
{
    "id": 22,
    "recv": [
        {
            "interface": "deposit",
            "result": "success"
        },
        {
            "interface": "query",
            "result": "",
            "balance": 620
        }
    ]
},
{
    "id": 23,
    "recv": [
        {
            "interface": "deposit",
            "result": "success"
        },
        {
            "interface": "query",
            "result": "",
            "balance": 630
        }
    ]
},
{
    "id": 24,
    "recv": [
        {
            "interface": "deposit",
            "result": "success"
        },
        {
            "interface": "query",
            "result": "",
            "balance": 640
        }
    ]
},
{
    "id": 25,
    "recv": [
        {
            "interface": "deposit",
            "result": "success"
        },
        {
            "interface": "query",
            "result": "",
            "balance": 650
        }
    ]
},
{
    "id": 26,
    "recv": [
        {
            "interface": "deposit",
            "result": "success"
        },
        {
            "interface": "query",
            "result": "",
            "balance": 660
        }
    ]
},
{
    "id": 27,
    "recv": [
        {
            "interface": "deposit",
            "result": "success"
        },
        {
            "interface": "query",
            "result": "",
            "balance": 670
        }
    ]
},
{
    "id": 28,
    "recv": [
        {
            "interface": "deposit",
            "result": "success"
        },
        {
            "interface": "query",
            "result": "",
            "balance": 680
        }
    ]
},
{
    "id": 29,
    "recv": [
        {
            "interface": "deposit",
            "result": "success"
        },
        {
            "interface": "query",
            "result": "",
            "balance": 690
        }
    ]
},
{
    "id": 30,
    "recv": [
        {
            "interface": "deposit",
            "result": "success"
        },
        {
            "interface": "query",
            "result": "",
            "balance": 700
        }
    ]
},
{
    "id": 31,
    "recv": [
        {
            "interface": "deposit",
            "result": "success"
        },
        {
            "interface": "query",
            "result": "",
            "balance": 710
        }
    ]
},
{
    "id": 32,
    "recv": [
        {
            "interface": "deposit",
            "result": "success"
        },
        {
            "interface": "query",
            "result": "",
            "balance": 720
        }
    ]
},
{
    "id": 33,
    "recv": [
        {
            "interface": "deposit",
            "result": "success"
        },
        {
            "interface": "query",
            "result": "",
            "balance": 730
        }
    ]
},
{
    "id": 34,
    "recv": [
        {
            "interface": "deposit",
            "result": "success"
        },
        {
            "interface": "query",
            "result": "",
            "balance": 740
        }
    ]
},
{
    "id": 35,
    "recv": [
        {
            "interface": "deposit",
            "result": "success"
        },
        {
            "interface": "query",
            "result": "",
            "balance": 750
        }
    ]
},
{
    "id": 36,
    "recv": [
        {
            "interface": "deposit",
            "result": "success"
        },
        {
            "interface": "query",
            "result": "",
            "balance": 760
        }
    ]
},
{
    "id": 37,
    "recv": [
        {
            "interface": "deposit",
            "result": "success"
        },
        {
            "interface": "query",
            "result": "",
            "balance": 770
        }
    ]
},
{
    "id": 38,
    "recv": [
        {
            "interface": "deposit",
            "result": "success"
        },
        {
            "interface": "query",
            "result": "",
            "balance": 780
        }
    ]
},
{
    "id": 39,
    "recv": [
        {
            "interface": "deposit",
            "result": "success"
        },
        {
            "interface": "query",
            "result": "",
            "balance": 790
        }
    ]
},
{
    "id": 40,
    "recv": [
        {
            "interface": "deposit",
            "result": "success"
        },
        {
            "interface": "query",
            "result": "",
            "balance": 800
        }
    ]
},
{
    "id": 41,
    "recv": [
        {
            "interface": "deposit",
            "result": "success"
        },
        {
            "interface": "query",
            "result": "",
            "balance": 810
        }
    ]
},
{
    "id": 42,
    "recv": [
        {
            "interface": "deposit",
            "result": "success"
        },
        {
            "interface": "query",
            "result": "",
            "balance": 820
        }
    ]
},
{
    "id": 43,
    "recv": [
        {
            "interface": "deposit",
            "result": "success"
        },
        {
            "interface": "query",
            "result": "",
            "balance": 830
        }
    ]
},
{
    "id": 44,
    "recv": [
        {
            "interface": "deposit",
            "result": "success"
        },
        {
            "interface": "query",
            "result": "",
            "balance": 840
        }
    ]
},
{
    "id": 45,
    "recv": [
        {
            "interface": "deposit",
            "result": "success"
        },
        {
            "interface": "query",
            "result": "",
            "balance": 850
        }
    ]
},
{
    "id": 46,
    "recv": [
        {
            "interface": "deposit",
            "result": "success"
        },
        {
            "interface": "query",
            "result": "",
            "balance": 860
        }
    ]
},
{
    "id": 47,
    "recv": [
        {
            "interface": "deposit",
            "result": "success"
        },
        {
            "interface": "query",
            "result": "",
            "balance": 870
        }
    ]
},
{
    "id": 48,
    "recv": [
        {
            "interface": "deposit",
            "result": "success"
        },
        {
            "interface": "query",
            "result": "",
            "balance": 880
        }
    ]
},
{
    "id": 49,
    "recv": [
        {
            "interface": "deposit",
            "result": "success"
        },
        {
            "interface": "query",
            "result": "",
            "balance": 890
        }
    ]
},
{
    "id": 50,
    "recv": [
        {
            "interface": "deposit",
            "result": "success"
        },
        {
            "interface": "query",
            "result": "",
            "balance": 900
        }
    ]
},
{
    "id": 1,
    "recv": [
        {
            "interface": "withdraw",
            "result": "success"
        },
        {
            "interface": "query",
            "result": "",
            "balance": 890
        }
    ]
},
{
    "id": 2,
    "recv": [
        {
            "interface": "withdraw",
            "result": "success"
        },
        {
            "interface": "query",
            "result": "",
            "balance": 880
        }
    ]
},
{
    "id": 3,
    "recv": [
        {
            "interface": "withdraw",
            "result": "success"
        },
        {
            "interface": "query",
            "result": "",
            "balance": 870
        }
    ]
},
{
    "id": 4,
    "recv": [
        {
            "interface": "withdraw",
            "result": "success"
        },
        {
            "interface": "query",
            "result": "",
            "balance": 860
        }
    ]
},
{
    "id": 5,
    "recv": [
        {
            "interface": "withdraw",
            "result": "success"
        },
        {
            "interface": "query",
            "result": "",
            "balance": 850
        }
    ]
},
{
    "id": 6,
    "recv": [
        {
            "interface": "withdraw",
            "result": "success"
        },
        {
            "interface": "query",
            "result": "",
            "balance": 840
        }
    ]
},
{
    "id": 7,
    "recv": [
        {
            "interface": "withdraw",
            "result": "success"
        },
        {
            "interface": "query",
            "result": "",
            "balance": 830
        }
    ]
},
{
    "id": 8,
    "recv": [
        {
            "interface": "withdraw",
            "result": "success"
        },
        {
            "interface": "query",
            "result": "",
            "balance": 820
        }
    ]
},
{
    "id": 9,
    "recv": [
        {
            "interface": "withdraw",
            "result": "success"
        },
        {
            "interface": "query",
            "result": "",
            "balance": 810
        }
    ]
},
{
    "id": 10,
    "recv": [
        {
            "interface": "withdraw",
            "result": "success"
        },
        {
            "interface": "query",
            "result": "",
            "balance": 800
        }
    ]
},
{
    "id": 11,
    "recv": [
        {
            "interface": "withdraw",
            "result": "success"
        },
        {
            "interface": "query",
            "result": "",
            "balance": 790
        }
    ]
},
{
    "id": 12,
    "recv": [
        {
            "interface": "withdraw",
            "result": "success"
        },
        {
            "interface": "query",
            "result": "",
            "balance": 780
        }
    ]
},
{
    "id": 13,
    "recv": [
        {
            "interface": "withdraw",
            "result": "success"
        },
        {
            "interface": "query",
            "result": "",
            "balance": 770
        }
    ]
},
{
    "id": 14,
    "recv": [
        {
            "interface": "withdraw",
            "result": "success"
        },
        {
            "interface": "query",
            "result": "",
            "balance": 760
        }
    ]
},
{
    "id": 15,
    "recv": [
        {
            "interface": "withdraw",
            "result": "success"
        },
        {
            "interface": "query",
            "result": "",
            "balance": 750
        }
    ]
},
{
    "id": 16,
    "recv": [
        {
            "interface": "withdraw",
            "result": "success"
        },
        {
            "interface": "query",
            "result": "",
            "balance": 740
        }
    ]
},
{
    "id": 17,
    "recv": [
        {
            "interface": "withdraw",
            "result": "success"
        },
        {
            "interface": "query",
            "result": "",
            "balance": 730
        }
    ]
},
{
    "id": 18,
    "recv": [
        {
            "interface": "withdraw",
            "result": "success"
        },
        {
            "interface": "query",
            "result": "",
            "balance": 720
        }
    ]
},
{
    "id": 19,
    "recv": [
        {
            "interface": "withdraw",
            "result": "success"
        },
        {
            "interface": "query",
            "result": "",
            "balance": 710
        }
    ]
},
{
    "id": 20,
    "recv": [
        {
            "interface": "withdraw",
            "result": "success"
        },
        {
            "interface": "query",
            "result": "",
            "balance": 700
        }
    ]
},
{
    "id": 21,
    "recv": [
        {
            "interface": "withdraw",
            "result": "success"
        },
        {
            "interface": "query",
            "result": "",
            "balance": 690
        }
    ]
},
{
    "id": 22,
    "recv": [
        {
            "interface": "withdraw",
            "result": "success"
        },
        {
            "interface": "query",
            "result": "",
            "balance": 680
        }
    ]
},
{
    "id": 23,
    "recv": [
        {
            "interface": "withdraw",
            "result": "success"
        },
        {
            "interface": "query",
            "result": "",
            "balance": 670
        }
    ]
},
{
    "id": 24,
    "recv": [
        {
            "interface": "withdraw",
            "result": "success"
        },
        {
            "interface": "query",
            "result": "",
            "balance": 660
        }
    ]
},
{
    "id": 25,
    "recv": [
        {
            "interface": "withdraw",
            "result": "success"
        },
        {
            "interface": "query",
            "result": "",
            "balance": 650
        }
    ]
},
{
    "id": 26,
    "recv": [
        {
            "interface": "withdraw",
            "result": "success"
        },
        {
            "interface": "query",
            "result": "",
            "balance": 640
        }
    ]
},
{
    "id": 27,
    "recv": [
        {
            "interface": "withdraw",
            "result": "success"
        },
        {
            "interface": "query",
            "result": "",
            "balance": 630
        }
    ]
},
{
    "id": 28,
    "recv": [
        {
            "interface": "withdraw",
            "result": "success"
        },
        {
            "interface": "query",
            "result": "",
            "balance": 620
        }
    ]
},
{
    "id": 29,
    "recv": [
        {
            "interface": "withdraw",
            "result": "success"
        },
        {
            "interface": "query",
            "result": "",
            "balance": 610
        }
    ]
},
{
    "id": 30,
    "recv": [
        {
            "interface": "withdraw",
            "result": "success"
        },
        {
            "interface": "query",
            "result": "",
            "balance": 600
        }
    ]
},
{
    "id": 31,
    "recv": [
        {
            "interface": "withdraw",
            "result": "success"
        },
        {
            "interface": "query",
            "result": "",
            "balance": 590
        }
    ]
},
{
    "id": 32,
    "recv": [
        {
            "interface": "withdraw",
            "result": "success"
        },
        {
            "interface": "query",
            "result": "",
            "balance": 580
        }
    ]
},
{
    "id": 33,
    "recv": [
        {
            "interface": "withdraw",
            "result": "success"
        },
        {
            "interface": "query",
            "result": "",
            "balance": 570
        }
    ]
},
{
    "id": 34,
    "recv": [
        {
            "interface": "withdraw",
            "result": "success"
        },
        {
            "interface": "query",
            "result": "",
            "balance": 560
        }
    ]
},
{
    "id": 35,
    "recv": [
        {
            "interface": "withdraw",
            "result": "success"
        },
        {
            "interface": "query",
            "result": "",
            "balance": 550
        }
    ]
},
{
    "id": 36,
    "recv": [
        {
            "interface": "withdraw",
            "result": "success"
        },
        {
            "interface": "query",
            "result": "",
            "balance": 540
        }
    ]
},
{
    "id": 37,
    "recv": [
        {
            "interface": "withdraw",
            "result": "success"
        },
        {
            "interface": "query",
            "result": "",
            "balance": 530
        }
    ]
},
{
    "id": 38,
    "recv": [
        {
            "interface": "withdraw",
            "result": "success"
        },
        {
            "interface": "query",
            "result": "",
            "balance": 520
        }
    ]
},
{
    "id": 39,
    "recv": [
        {
            "interface": "withdraw",
            "result": "success"
        },
        {
            "interface": "query",
            "result": "",
            "balance": 510
        }
    ]
},
{
    "id": 40,
    "recv": [
        {
            "interface": "withdraw",
            "result": "success"
        },
        {
            "interface": "query",
            "result": "",
            "balance": 500
        }
    ]
},
{
    "id": 41,
    "recv": [
        {
            "interface": "withdraw",
            "result": "success"
        },
        {
            "interface": "query",
            "result": "",
            "balance": 490
        }
    ]
},
{
    "id": 42,
    "recv": [
        {
            "interface": "withdraw",
            "result": "success"
        },
        {
            "interface": "query",
            "result": "",
            "balance": 480
        }
    ]
},
{
    "id": 43,
    "recv": [
        {
            "interface": "withdraw",
            "result": "success"
        },
        {
            "interface": "query",
            "result": "",
            "balance": 470
        }
    ]
},
{
    "id": 44,
    "recv": [
        {
            "interface": "withdraw",
            "result": "success"
        },
        {
            "interface": "query",
            "result": "",
            "balance": 460
        }
    ]
},
{
    "id": 45,
    "recv": [
        {
            "interface": "withdraw",
            "result": "success"
        },
        {
            "interface": "query",
            "result": "",
            "balance": 450
        }
    ]
},
{
    "id": 46,
    "recv": [
        {
            "interface": "withdraw",
            "result": "success"
        },
        {
            "interface": "query",
            "result": "",
            "balance": 440
        }
    ]
},
{
    "id": 47,
    "recv": [
        {
            "interface": "withdraw",
            "result": "success"
        },
        {
            "interface": "query",
            "result": "",
            "balance": 430
        }
    ]
},
{
    "id": 48,
    "recv": [
        {
            "interface": "withdraw",
            "result": "success"
        },
        {
            "interface": "query",
            "result": "",
            "balance": 420
        }
    ]
},
{
    "id": 49,
    "recv": [
        {
            "interface": "withdraw",
            "result": "success"
        },
        {
            "interface": "query",
            "result": "",
            "balance": 410
        }
    ]
},
{
    "id": 50,
    "recv": [
        {
            "interface": "withdraw",
            "result": "success"
        },
        {
            "interface": "query",
            "result": "",
            "balance": 400
        }
    ]
}
]
